i3_focus_group/__init__.py
i3_focus_group/_version.py
i3_focus_group/main.py
i3_focus_group-0.1.5.dist-info/LICENSE
i3_focus_group-0.1.5.dist-info/METADATA
i3_focus_group-0.1.5.dist-info/WHEEL
i3_focus_group-0.1.5.dist-info/entry_points.txt
i3_focus_group-0.1.5.dist-info/top_level.txt
i3_focus_group-0.1.5.dist-info/RECORD
