Metadata-Version: 2.1
Name: i3-focus-group
Version: 0.1.5
Summary: Create a group for i3/sway containers to easily switch focus between
Home-page: https://github.com/DCsunset/i3-focus-group
Author: DCsunset
Author-email: DCsunset@protonmail.com
License: AGPL-3.0
Classifier: Environment :: Console
Classifier: Intended Audience :: End Users/Desktop
Classifier: Programming Language :: Python
Classifier: License :: OSI Approved :: GNU Affero General Public License v3
Classifier: Topic :: Desktop Environment :: Window Managers
Classifier: Topic :: Utilities
License-File: LICENSE
Requires-Dist: i3ipc >=2.2.1
